brt/__init__.py
brt-0.0.1b11.dist-info/LICENSE
brt-0.0.1b11.dist-info/METADATA
brt-0.0.1b11.dist-info/WHEEL
brt-0.0.1b11.dist-info/top_level.txt
brt-0.0.1b11.dist-info/RECORD
